cv_image_suit/__init__.py
cv_image_suit/main.py
cv_image_suit/Config_Layer/configs.json
cv_image_suit/Config_Layer/experiment_inputs_configs.json
cv_image_suit/Config_Layer/experiment_result.json
cv_image_suit/Config_Layer/pred_configs.json
cv_image_suit/Exception_Layer/__init__.py
cv_image_suit/Exception_Layer/exception.py
cv_image_suit/Experiment_Layer/__init__.py
cv_image_suit/Experiment_Layer/model_finder.py
cv_image_suit/Logging_Layer/__init__.py
cv_image_suit/Logging_Layer/logger.py
cv_image_suit/Logs/logs.txt
cv_image_suit/Prediction_Layer/__init__.py
cv_image_suit/Prediction_Layer/predict.py
cv_image_suit/Training_Layer/__init__.py
cv_image_suit/Training_Layer/train_engine.py
cv_image_suit/com_in_ineuron_ai_utils/__init__.py
cv_image_suit/com_in_ineuron_ai_utils/utils.py
cv_image_suit/static/assets/favicon.ico
cv_image_suit/static/assets/img/bg-masthead.jpg
cv_image_suit/static/assets/img/cv_image_suit.png
cv_image_suit/static/assets/img/form-v9.jpg
cv_image_suit/static/assets/img/portfolio/fullsize/1.jpg
cv_image_suit/static/assets/img/portfolio/fullsize/2.jpg
cv_image_suit/static/assets/img/portfolio/fullsize/3.jpg
cv_image_suit/static/assets/img/portfolio/fullsize/4.jpg
cv_image_suit/static/assets/img/portfolio/fullsize/5.jpg
cv_image_suit/static/assets/img/portfolio/fullsize/6.jpg
cv_image_suit/static/assets/img/portfolio/thumbnails/1.jpg
cv_image_suit/static/assets/img/portfolio/thumbnails/2.jpg
cv_image_suit/static/assets/img/portfolio/thumbnails/3.jpg
cv_image_suit/static/assets/img/portfolio/thumbnails/4.jpg
cv_image_suit/static/assets/img/portfolio/thumbnails/5.jpg
cv_image_suit/static/assets/img/portfolio/thumbnails/6.jpg
cv_image_suit/static/css/styles.css
cv_image_suit/static/css2/nunito-font.css
cv_image_suit/static/css2/style.css
cv_image_suit/static/js/scripts.js
cv_image_suit/templates/experiment_log.html
cv_image_suit/templates/experiment_output.html
cv_image_suit/templates/index.html
cv_image_suit/templates/input_experiments.html
cv_image_suit-0.99.1.dist-info/LICENSE
cv_image_suit-0.99.1.dist-info/METADATA
cv_image_suit-0.99.1.dist-info/WHEEL
cv_image_suit-0.99.1.dist-info/entry_points.txt
cv_image_suit-0.99.1.dist-info/top_level.txt
cv_image_suit-0.99.1.dist-info/RECORD
