Metadata-Version: 2.1
Name: cv-image-suit
Version: 0.99.1
Summary: Its an auto image classification and experimentation library
Home-page: https://github.com/uday446/cv_image_suit
Author: Udayrajsinh Jadeja
Author-email: ujadeja96@gmail.com
License: GNU
Keywords: cv_image_suit
Classifier: Development Status :: 3 - Alpha
Classifier: Intended Audience :: Developers
Classifier: Topic :: Software Development :: Build Tools
Classifier: License :: OSI Approved :: GNU General Public License v3 (GPLv3)
Classifier: Programming Language :: Python :: 3
Classifier: Programming Language :: Python :: 3.4
Classifier: Programming Language :: Python :: 3.5
Classifier: Programming Language :: Python :: 3.6
Classifier: Programming Language :: Python :: 3.7
License-File: LICENSE
Requires-Dist: tensorflow (==2.9.1)
Requires-Dist: scipy
Requires-Dist: numpy
Requires-Dist: pandas
Requires-Dist: Pillow (==8.3.2)
Requires-Dist: fastapi
